PickPlace3D/__init__.py
PickPlace3D-0.0.1.2.dist-info/LICENSE
PickPlace3D-0.0.1.2.dist-info/METADATA
PickPlace3D-0.0.1.2.dist-info/WHEEL
PickPlace3D-0.0.1.2.dist-info/top_level.txt
PickPlace3D-0.0.1.2.dist-info/RECORD
