Metadata-Version: 2.1
Name: PickPlace3D
Version: 0.0.1.2
Summary: Pick and place using 3D data to inform robotic movement
Home-page: https://github.com/i3drobotics/PickPlace3D
Author: Ben Knight
Author-email: bknight@i3drobotics.com
License: UNKNOWN
Platform: UNKNOWN
Classifier: Programming Language :: Python :: 3
Classifier: License :: OSI Approved :: MIT License
Classifier: Operating System :: OS Independent
Requires-Python: >=3.6
Requires-Dist: numpy
Requires-Dist: opencv-python
Requires-Dist: stereocapture
